restapi_echo_server/__init__.py
restapi_echo_server/__main__.py
restapi_echo_server/server.py
restapi_echo_server-0.4.0.dist-info/LICENSE
restapi_echo_server-0.4.0.dist-info/WHEEL
restapi_echo_server-0.4.0.dist-info/METADATA
restapi_echo_server-0.4.0.dist-info/RECORD
